gastop/__init__.py
gastop/__main__.py
gastop/crossover.py
gastop/encoders.py
gastop/evaluator.py
gastop/fitness.py
gastop/genalg.py
gastop/mutator.py
gastop/progmon.py
gastop/selector.py
gastop/truss.py
gastop/utilities.py
gastop-1.0.2.dist-info/METADATA
gastop-1.0.2.dist-info/RECORD
gastop-1.0.2.dist-info/WHEEL
gastop-1.0.2.dist-info/entry_points.txt
gastop-1.0.2.dist-info/top_level.txt
