Metadata-Version: 2.1
Name: gastop
Version: 1.0.2
Summary: A Genetic Algorithm for Structural Design and Topological Optimization
Home-page: https://github.com/f0uriest/GASTOp/
Author: Rory Conlin, Paul Kaneelil, Cristian Lacey, Susan Redmond, Dan Shaw, Amlan Sinha
Author-email: wconlin@princeton.edu
License: UNKNOWN
Project-URL: Bug Reports, https://github.com/f0uriest/GASTOp/issues
Project-URL: Source, https://github.com/f0uriest/GASTOp/
Project-URL: Documentation, https://gastop.readthedocs.io
Keywords: genetic algorithm structure structural analysis design optimization topology
Platform: UNKNOWN
Classifier: Development Status :: 5 - Production/Stable
Classifier: Intended Audience :: Education
Classifier: Intended Audience :: End Users/Desktop
Classifier: Intended Audience :: Manufacturing
Classifier: Intended Audience :: Science/Research
Classifier: Topic :: Education :: Computer Aided Instruction (CAI)
Classifier: Topic :: Scientific/Engineering :: Artificial Intelligence
Classifier: Topic :: Scientific/Engineering
Classifier: License :: OSI Approved :: GNU General Public License v3 (GPLv3)
Classifier: Natural Language :: English
Classifier: Programming Language :: Python :: 3
Classifier: Programming Language :: Python :: 3.5
Classifier: Programming Language :: Python :: 3.6
Classifier: Programming Language :: Python :: 3.7
Provides-Extra: dev
Provides-Extra: test
Requires-Dist: numpy
Requires-Dist: matplotlib
Requires-Dist: configobj
Requires-Dist: tqdm
Requires-Dist: colorama
Requires-Dist: imageio
Provides-Extra: dev
Requires-Dist: check-manifest; extra == 'dev'
Provides-Extra: test
Requires-Dist: pytest; extra == 'test'
Requires-Dist: pytest-cov; extra == 'test'
